beautiful_oops/__init__.py
beautiful_oops/decorators.py
beautiful_oops/core/adventure.py
beautiful_oops/core/elf.py
beautiful_oops/core/hero.py
beautiful_oops/core/moment.py
beautiful_oops/core/oops.py
beautiful_oops/integrations/fastapi/middleware.py
beautiful_oops/plugins/storybook_console_sink_plugin.py
beautiful_oops/plugins/storybook_plugin.py
beautiful_oops/plugins/tracing_stack_plugin.py
beautiful_oops/plugins/models/storybook.py
beautiful_oops/utils/trace_id_generator.py
beautiful_oops-0.1.7.dist-info/licenses/LICENSE
beautiful_oops-0.1.7.dist-info/METADATA
beautiful_oops-0.1.7.dist-info/WHEEL
beautiful_oops-0.1.7.dist-info/top_level.txt
beautiful_oops-0.1.7.dist-info/RECORD
