Metadata-Version: 2.4
Name: beautiful-oops
Version: 0.1.7
Summary: A gentle, story-driven supervision and recovery framework for Python — because every error deserves a story.
Author-email: Sean Liu <seanliu@nemovideo.com>
License: MIT
Requires-Python: >=3.10
License-File: LICENSE
Requires-Dist: fastapi>=0.110
Requires-Dist: starlette>=0.37
Provides-Extra: dev
Requires-Dist: pytest>=7.0; extra == "dev"
Requires-Dist: pytest-asyncio>=0.23; extra == "dev"
Requires-Dist: mypy>=1.8; extra == "dev"
Requires-Dist: ruff>=0.6; extra == "dev"
Requires-Dist: fastapi>=0.110; extra == "dev"
Requires-Dist: starlette>=0.37; extra == "dev"
Dynamic: license-file
